{
  "id" : "Personal",
  "name" : "Personal",
  "type" : "fragment",
  "modelVersion" : "2.4",
  "lastUpdate" : 1709792634337,
  "rows" : [
    [
      {
        "type" : "component",
        "dimension" : {
          "md" : 12,
          "sm" : 12,
          "xs" : 12,
          "lg" : 12
        },
        "propertyValues" : {
          "hidden" : {
            "type" : "constant",
            "value" : false
          },
          "level" : {
            "type" : "constant",
            "value" : "Level 4"
          },
          "cssClasses" : {
            "type" : "constant",
            "value" : ""
          },
          "text" : {
            "type" : "interpolation",
            "value" : "Personal"
          },
          "alignment" : {
            "type" : "constant",
            "value" : "left"
          },
          "dimension" : {
            "type" : "constant",
            "value" : 12
          },
          "allowHTML" : {
            "type" : "constant",
            "value" : false
          }
        },
        "reference" : "e679becf-3200-4956-8357-ac9da2c4e5b3",
        "hasValidationError" : false,
        "id" : "pbTitle",
        "description" : ""
      }
    ],
    [
      {
        "type" : "container",
        "dimension" : {
          "xs" : 12,
          "sm" : 12,
          "md" : 12,
          "lg" : 12
        },
        "propertyValues" : {
          "cssClasses" : {
            "type" : "constant",
            "value" : ""
          },
          "hidden" : {
            "type" : "expression",
            "value" : "mode!=\"edit\""
          },
          "repeatedCollection" : {
            "type" : "variable"
          }
        },
        "reference" : "9758bbc7-45f6-45c4-86f8-3383a073e7db",
        "hasValidationError" : false,
        "id" : "pbContainer",
        "rows" : [
          [
            {
              "type" : "component",
              "dimension" : {
                "md" : 12,
                "sm" : 12,
                "xs" : 12,
                "lg" : 12
              },
              "propertyValues" : {
                "labelHidden" : {
                  "type" : "constant",
                  "value" : false
                },
                "hidden" : {
                  "type" : "constant",
                  "value" : false
                },
                "labelPosition" : {
                  "type" : "constant",
                  "value" : "top"
                },
                "cssClasses" : {
                  "type" : "constant",
                  "value" : ""
                },
                "labelWidth" : {
                  "type" : "constant",
                  "value" : 1
                },
                "readOnly" : {
                  "type" : "constant",
                  "value" : false
                },
                "label" : {
                  "type" : "interpolation",
                  "value" : "Nama Lengkap"
                },
                "placeholder" : {
                  "type" : "constant"
                },
                "type" : {
                  "type" : "constant",
                  "value" : "text"
                },
                "dimension" : {
                  "type" : "constant",
                  "value" : 12
                },
                "value" : {
                  "type" : "variable",
                  "value" : "personal.namaLengkap"
                },
                "required" : {
                  "type" : "constant",
                  "value" : true
                },
                "allowHTML" : {
                  "type" : "constant",
                  "value" : false
                },
                "minLength" : {
                  "type" : "constant",
                  "value" : ""
                },
                "maxLength" : {
                  "type" : "constant",
                  "value" : ""
                },
                "debounce" : {
                  "type" : "constant",
                  "value" : 0
                },
                "min" : {
                  "type" : "constant"
                },
                "max" : {
                  "type" : "constant"
                },
                "step" : {
                  "type" : "constant",
                  "value" : 1
                }
              },
              "reference" : "8945f3f5-ee18-4182-ab7c-1f58e6fb9555",
              "hasValidationError" : false,
              "id" : "pbInput",
              "description" : ""
            }
          ],
          [
            {
              "type" : "component",
              "dimension" : {
                "xs" : 12,
                "sm" : 12,
                "md" : 6,
                "lg" : 6
              },
              "propertyValues" : {
                "cssClasses" : {
                  "type" : "constant",
                  "value" : ""
                },
                "hidden" : {
                  "type" : "constant",
                  "value" : false
                },
                "required" : {
                  "type" : "constant",
                  "value" : true
                },
                "allowHTML" : {
                  "type" : "constant",
                  "value" : false
                },
                "minLength" : {
                  "type" : "constant",
                  "value" : ""
                },
                "maxLength" : {
                  "type" : "constant",
                  "value" : ""
                },
                "readOnly" : {
                  "type" : "constant",
                  "value" : false
                },
                "labelHidden" : {
                  "type" : "constant",
                  "value" : false
                },
                "label" : {
                  "type" : "interpolation",
                  "value" : "Tempat Lahir"
                },
                "labelPosition" : {
                  "type" : "constant",
                  "value" : "top"
                },
                "labelWidth" : {
                  "type" : "constant",
                  "value" : 4
                },
                "placeholder" : {
                  "type" : "interpolation"
                },
                "value" : {
                  "type" : "variable",
                  "value" : "personal.tempatLahir"
                },
                "debounce" : {
                  "type" : "constant",
                  "value" : 0
                },
                "type" : {
                  "type" : "constant",
                  "value" : "text"
                },
                "min" : {
                  "type" : "constant"
                },
                "max" : {
                  "type" : "constant"
                },
                "step" : {
                  "type" : "constant",
                  "value" : 1
                }
              },
              "reference" : "66164137-0e8a-42c4-bc72-2d11e3199005",
              "hasValidationError" : false,
              "id" : "pbInput"
            },
            {
              "type" : "component",
              "dimension" : {
                "md" : 6,
                "sm" : 12,
                "xs" : 12,
                "lg" : 6
              },
              "propertyValues" : {
                "hidden" : {
                  "type" : "constant",
                  "value" : false
                },
                "dateFormat" : {
                  "type" : "constant",
                  "value" : "dd-MM-yyyy"
                },
                "cssClasses" : {
                  "type" : "constant",
                  "value" : ""
                },
                "labelWidth" : {
                  "type" : "constant",
                  "value" : 1
                },
                "readOnly" : {
                  "type" : "constant",
                  "value" : false
                },
                "label" : {
                  "type" : "interpolation",
                  "value" : "Tanggal Lahir"
                },
                "type" : {
                  "type" : "constant"
                },
                "required" : {
                  "type" : "constant",
                  "value" : true
                },
                "todayLabel" : {
                  "type" : "constant",
                  "value" : "Today"
                },
                "labelHidden" : {
                  "type" : "constant",
                  "value" : false
                },
                "showToday" : {
                  "type" : "constant",
                  "value" : false
                },
                "labelPosition" : {
                  "type" : "constant",
                  "value" : "top"
                },
                "placeholder" : {
                  "type" : "constant",
                  "value" : "Masukan tanggal (dd-mm-yyyy)"
                },
                "dimension" : {
                  "type" : "constant",
                  "value" : 12
                },
                "value" : {
                  "type" : "variable",
                  "value" : "personal.tglLahir"
                },
                "allowHTML" : {
                  "type" : "constant",
                  "value" : false
                }
              },
              "reference" : "3acfedea-e9b2-4623-98e7-b32e15a491ba",
              "hasValidationError" : false,
              "id" : "pbDatePicker",
              "description" : ""
            }
          ],
          [
            {
              "type" : "component",
              "dimension" : {
                "md" : 6,
                "sm" : 12,
                "xs" : 12,
                "lg" : 6
              },
              "propertyValues" : {
                "cssClasses" : {
                  "type" : "constant",
                  "value" : ""
                },
                "hidden" : {
                  "type" : "constant",
                  "value" : false
                },
                "disabled" : {
                  "type" : "constant",
                  "value" : false
                },
                "required" : {
                  "type" : "constant",
                  "value" : true
                },
                "allowHTML" : {
                  "type" : "constant",
                  "value" : false
                },
                "labelHidden" : {
                  "type" : "constant",
                  "value" : false
                },
                "label" : {
                  "type" : "interpolation",
                  "value" : "Jenis Kelamin"
                },
                "labelPosition" : {
                  "type" : "constant",
                  "value" : "top"
                },
                "labelWidth" : {
                  "type" : "constant",
                  "value" : 1
                },
                "placeholder" : {
                  "type" : "interpolation"
                },
                "availableValues" : {
                  "type" : "expression",
                  "value" : "options.jenisKelamin"
                },
                "displayedKey" : {
                  "type" : "constant"
                },
                "returnedKey" : {
                  "type" : "constant"
                },
                "value" : {
                  "type" : "variable",
                  "value" : "personal.jenisKelamin"
                }
              },
              "reference" : "acbf58eb-696e-451c-8bf5-5586ec4b7ab6",
              "hasValidationError" : false,
              "id" : "pbSelect"
            },
            {
              "type" : "component",
              "dimension" : {
                "md" : 6,
                "sm" : 12,
                "xs" : 12,
                "lg" : 6
              },
              "propertyValues" : {
                "cssClasses" : {
                  "type" : "constant",
                  "value" : ""
                },
                "hidden" : {
                  "type" : "constant",
                  "value" : false
                },
                "disabled" : {
                  "type" : "constant",
                  "value" : false
                },
                "required" : {
                  "type" : "constant",
                  "value" : true
                },
                "allowHTML" : {
                  "type" : "constant",
                  "value" : false
                },
                "labelHidden" : {
                  "type" : "constant",
                  "value" : false
                },
                "label" : {
                  "type" : "interpolation",
                  "value" : "Status Pernikahan"
                },
                "labelPosition" : {
                  "type" : "constant",
                  "value" : "top"
                },
                "labelWidth" : {
                  "type" : "constant",
                  "value" : 1
                },
                "placeholder" : {
                  "type" : "interpolation"
                },
                "availableValues" : {
                  "type" : "expression",
                  "value" : "options.status"
                },
                "displayedKey" : {
                  "type" : "constant"
                },
                "returnedKey" : {
                  "type" : "constant"
                },
                "value" : {
                  "type" : "variable",
                  "value" : "personal.statusPernikahan"
                }
              },
              "reference" : "b1ffe11d-750e-4e56-8cb7-1aeb4bb50204",
              "hasValidationError" : false,
              "id" : "pbSelect"
            }
          ],
          [
            {
              "type" : "component",
              "dimension" : {
                "md" : 6,
                "sm" : 12,
                "xs" : 12,
                "lg" : 6
              },
              "propertyValues" : {
                "labelHidden" : {
                  "type" : "constant",
                  "value" : false
                },
                "hidden" : {
                  "type" : "constant",
                  "value" : false
                },
                "labelPosition" : {
                  "type" : "constant",
                  "value" : "top"
                },
                "cssClasses" : {
                  "type" : "constant",
                  "value" : ""
                },
                "labelWidth" : {
                  "type" : "constant",
                  "value" : 1
                },
                "readOnly" : {
                  "type" : "constant",
                  "value" : false
                },
                "label" : {
                  "type" : "interpolation",
                  "value" : "No. KTP"
                },
                "placeholder" : {
                  "type" : "constant"
                },
                "type" : {
                  "type" : "constant",
                  "value" : "text"
                },
                "dimension" : {
                  "type" : "constant",
                  "value" : 12
                },
                "value" : {
                  "type" : "variable",
                  "value" : "personal.noKTP"
                },
                "required" : {
                  "type" : "constant",
                  "value" : true
                },
                "allowHTML" : {
                  "type" : "constant",
                  "value" : false
                },
                "minLength" : {
                  "type" : "constant",
                  "value" : 16
                },
                "maxLength" : {
                  "type" : "constant",
                  "value" : 16
                },
                "debounce" : {
                  "type" : "constant",
                  "value" : 0
                },
                "min" : {
                  "type" : "constant"
                },
                "max" : {
                  "type" : "constant"
                },
                "step" : {
                  "type" : "constant",
                  "value" : 1
                }
              },
              "reference" : "c7e9fb41-e45a-4479-89ea-020a2bb15b4b",
              "hasValidationError" : false,
              "id" : "pbInput",
              "description" : ""
            },
            {
              "type" : "component",
              "dimension" : {
                "md" : 6,
                "sm" : 12,
                "xs" : 12,
                "lg" : 6
              },
              "propertyValues" : {
                "cssClasses" : {
                  "type" : "constant",
                  "value" : ""
                },
                "hidden" : {
                  "type" : "constant",
                  "value" : false
                },
                "disabled" : {
                  "type" : "constant",
                  "value" : false
                },
                "required" : {
                  "type" : "constant",
                  "value" : true
                },
                "allowHTML" : {
                  "type" : "constant",
                  "value" : false
                },
                "labelHidden" : {
                  "type" : "constant",
                  "value" : false
                },
                "label" : {
                  "type" : "interpolation",
                  "value" : "Jabatan"
                },
                "labelPosition" : {
                  "type" : "constant",
                  "value" : "top"
                },
                "labelWidth" : {
                  "type" : "constant",
                  "value" : 1
                },
                "placeholder" : {
                  "type" : "interpolation"
                },
                "availableValues" : {
                  "type" : "expression",
                  "value" : "listJabatan"
                },
                "displayedKey" : {
                  "type" : "constant",
                  "value" : "displayName"
                },
                "returnedKey" : {
                  "type" : "constant",
                  "value" : "id"
                },
                "value" : {
                  "type" : "variable",
                  "value" : "personal.jabatan"
                }
              },
              "reference" : "cb65d8b0-8c19-4e75-a0c4-eb9ebf116a99",
              "hasValidationError" : false,
              "id" : "pbSelect"
            }
          ],
          [
            {
              "type" : "component",
              "dimension" : {
                "xs" : 12,
                "sm" : 12,
                "md" : 6,
                "lg" : 12
              },
              "propertyValues" : {
                "cssClasses" : {
                  "type" : "constant",
                  "value" : ""
                },
                "hidden" : {
                  "type" : "constant",
                  "value" : false
                },
                "readOnly" : {
                  "type" : "constant",
                  "value" : false
                },
                "required" : {
                  "type" : "constant",
                  "value" : true
                },
                "allowHTML" : {
                  "type" : "constant",
                  "value" : false
                },
                "labelHidden" : {
                  "type" : "constant",
                  "value" : false
                },
                "label" : {
                  "type" : "interpolation",
                  "value" : "Mulai Bekerja"
                },
                "labelPosition" : {
                  "type" : "constant",
                  "value" : "top"
                },
                "labelWidth" : {
                  "type" : "constant",
                  "value" : 4
                },
                "value" : {
                  "type" : "variable",
                  "value" : "personal.tglMulaiKerja"
                },
                "dateFormat" : {
                  "type" : "constant",
                  "value" : "dd-MM-yyyy"
                },
                "placeholder" : {
                  "type" : "interpolation",
                  "value" : "Masukan tanggal (dd-mm-yyyy)"
                },
                "showToday" : {
                  "type" : "constant",
                  "value" : false
                },
                "todayLabel" : {
                  "type" : "interpolation",
                  "value" : "Today"
                }
              },
              "reference" : "cc30e78f-47d3-457e-8c45-a5b5c1b83b9c",
              "hasValidationError" : false,
              "id" : "pbDatePicker"
            }
          ]
        ]
      }
    ],
    [
      {
        "type" : "container",
        "dimension" : {
          "xs" : 12,
          "sm" : 12,
          "md" : 12,
          "lg" : 12
        },
        "propertyValues" : {
          "cssClasses" : {
            "type" : "constant",
            "value" : ""
          },
          "hidden" : {
            "type" : "expression",
            "value" : "mode!=\"view\""
          },
          "repeatedCollection" : {
            "type" : "variable"
          }
        },
        "reference" : "809c5cf1-ced0-43d6-a1f0-f43851be052f",
        "hasValidationError" : false,
        "id" : "pbContainer",
        "rows" : [
          [
            {
              "type" : "component",
              "dimension" : {
                "xs" : 12,
                "sm" : 12,
                "md" : 6,
                "lg" : 6
              },
              "propertyValues" : {
                "cssClasses" : {
                  "type" : "constant",
                  "value" : ""
                },
                "hidden" : {
                  "type" : "constant",
                  "value" : false
                },
                "allowHTML" : {
                  "type" : "constant",
                  "value" : false
                },
                "labelHidden" : {
                  "type" : "constant",
                  "value" : false
                },
                "label" : {
                  "type" : "interpolation",
                  "value" : "Nama Lengkap"
                },
                "labelPosition" : {
                  "type" : "constant",
                  "value" : "top"
                },
                "labelWidth" : {
                  "type" : "constant",
                  "value" : 12
                },
                "text" : {
                  "type" : "interpolation",
                  "value" : "{{personal.namaLengkap}}"
                },
                "alignment" : {
                  "type" : "constant",
                  "value" : "left"
                }
              },
              "reference" : "bf69429c-17e2-4142-a4be-e32b11a8b0d1",
              "hasValidationError" : false,
              "id" : "pbText"
            },
            {
              "type" : "component",
              "dimension" : {
                "xs" : 12,
                "sm" : 12,
                "md" : 6,
                "lg" : 6
              },
              "propertyValues" : {
                "cssClasses" : {
                  "type" : "constant",
                  "value" : ""
                },
                "hidden" : {
                  "type" : "constant",
                  "value" : false
                },
                "allowHTML" : {
                  "type" : "constant",
                  "value" : false
                },
                "labelHidden" : {
                  "type" : "constant",
                  "value" : false
                },
                "label" : {
                  "type" : "interpolation",
                  "value" : "Tempat / Tanggal Lahir"
                },
                "labelPosition" : {
                  "type" : "constant",
                  "value" : "top"
                },
                "labelWidth" : {
                  "type" : "constant",
                  "value" : 12
                },
                "text" : {
                  "type" : "interpolation",
                  "value" : "{{personal.tempatLahir}} / {{personal.tglLahir | date:\"dd MMM yyyy\"}}"
                },
                "alignment" : {
                  "type" : "constant",
                  "value" : "left"
                }
              },
              "reference" : "9c804fab-3109-4521-97fc-d0e7b7e56914",
              "hasValidationError" : false,
              "id" : "pbText"
            }
          ],
          [
            {
              "type" : "component",
              "dimension" : {
                "xs" : 12,
                "sm" : 12,
                "md" : 6,
                "lg" : 6
              },
              "propertyValues" : {
                "cssClasses" : {
                  "type" : "constant",
                  "value" : ""
                },
                "hidden" : {
                  "type" : "constant",
                  "value" : false
                },
                "allowHTML" : {
                  "type" : "constant",
                  "value" : false
                },
                "labelHidden" : {
                  "type" : "constant",
                  "value" : false
                },
                "label" : {
                  "type" : "interpolation",
                  "value" : "Jenis Kelamin"
                },
                "labelPosition" : {
                  "type" : "constant",
                  "value" : "top"
                },
                "labelWidth" : {
                  "type" : "constant",
                  "value" : 12
                },
                "text" : {
                  "type" : "interpolation",
                  "value" : "{{personal.jenisKelamin}}"
                },
                "alignment" : {
                  "type" : "constant",
                  "value" : "left"
                }
              },
              "reference" : "e427db70-4191-43be-b0c0-241509ecf979",
              "hasValidationError" : false,
              "id" : "pbText"
            },
            {
              "type" : "component",
              "dimension" : {
                "xs" : 12,
                "sm" : 12,
                "md" : 6,
                "lg" : 6
              },
              "propertyValues" : {
                "cssClasses" : {
                  "type" : "constant",
                  "value" : ""
                },
                "hidden" : {
                  "type" : "constant",
                  "value" : false
                },
                "allowHTML" : {
                  "type" : "constant",
                  "value" : false
                },
                "labelHidden" : {
                  "type" : "constant",
                  "value" : false
                },
                "label" : {
                  "type" : "interpolation",
                  "value" : "Status Pernikahan"
                },
                "labelPosition" : {
                  "type" : "constant",
                  "value" : "top"
                },
                "labelWidth" : {
                  "type" : "constant",
                  "value" : 12
                },
                "text" : {
                  "type" : "interpolation",
                  "value" : "{{personal.statusPernikahan}}"
                },
                "alignment" : {
                  "type" : "constant",
                  "value" : "left"
                }
              },
              "reference" : "8574c445-a80f-453d-9287-fba9256c5f52",
              "hasValidationError" : false,
              "id" : "pbText"
            }
          ],
          [
            {
              "type" : "component",
              "dimension" : {
                "xs" : 12,
                "sm" : 12,
                "md" : 6,
                "lg" : 6
              },
              "propertyValues" : {
                "cssClasses" : {
                  "type" : "constant",
                  "value" : ""
                },
                "hidden" : {
                  "type" : "constant",
                  "value" : false
                },
                "allowHTML" : {
                  "type" : "constant",
                  "value" : false
                },
                "labelHidden" : {
                  "type" : "constant",
                  "value" : false
                },
                "label" : {
                  "type" : "interpolation",
                  "value" : "No. KTP"
                },
                "labelPosition" : {
                  "type" : "constant",
                  "value" : "top"
                },
                "labelWidth" : {
                  "type" : "constant",
                  "value" : 12
                },
                "text" : {
                  "type" : "interpolation",
                  "value" : "{{personal.noKTP}}"
                },
                "alignment" : {
                  "type" : "constant",
                  "value" : "left"
                }
              },
              "reference" : "185c5612-c331-477f-84c1-97dddb6f40cd",
              "hasValidationError" : false,
              "id" : "pbText"
            },
            {
              "type" : "component",
              "dimension" : {
                "xs" : 12,
                "sm" : 12,
                "md" : 6,
                "lg" : 6
              },
              "propertyValues" : {
                "cssClasses" : {
                  "type" : "constant",
                  "value" : ""
                },
                "hidden" : {
                  "type" : "constant",
                  "value" : false
                },
                "allowHTML" : {
                  "type" : "constant",
                  "value" : false
                },
                "labelHidden" : {
                  "type" : "constant",
                  "value" : false
                },
                "label" : {
                  "type" : "interpolation",
                  "value" : "Jabatan"
                },
                "labelPosition" : {
                  "type" : "constant",
                  "value" : "top"
                },
                "labelWidth" : {
                  "type" : "constant",
                  "value" : 12
                },
                "text" : {
                  "type" : "interpolation",
                  "value" : "{{personal.jabatan}}"
                },
                "alignment" : {
                  "type" : "constant",
                  "value" : "left"
                }
              },
              "reference" : "4118d578-eaa1-41ce-aa6d-52f3b955c298",
              "hasValidationError" : false,
              "id" : "pbText"
            }
          ],
          [
            {
              "type" : "component",
              "dimension" : {
                "xs" : 12,
                "sm" : 12,
                "md" : 6,
                "lg" : 12
              },
              "propertyValues" : {
                "cssClasses" : {
                  "type" : "constant",
                  "value" : ""
                },
                "hidden" : {
                  "type" : "constant",
                  "value" : false
                },
                "allowHTML" : {
                  "type" : "constant",
                  "value" : false
                },
                "labelHidden" : {
                  "type" : "constant",
                  "value" : false
                },
                "label" : {
                  "type" : "interpolation",
                  "value" : "Mulai Bekerja"
                },
                "labelPosition" : {
                  "type" : "constant",
                  "value" : "top"
                },
                "labelWidth" : {
                  "type" : "constant",
                  "value" : 12
                },
                "text" : {
                  "type" : "interpolation",
                  "value" : "{{personal.tglMulaiKerja | date:\"dd MMM yyyy\"}}"
                },
                "alignment" : {
                  "type" : "constant",
                  "value" : "left"
                }
              },
              "reference" : "b658cefd-fd1c-4594-b13a-558aa5cc1f17",
              "hasValidationError" : false,
              "id" : "pbText"
            }
          ]
        ]
      }
    ]
  ],
  "variables" : {
    "personal" : {
      "type" : "constant",
      "value" : [
        ""
      ],
      "exposed" : true
    },
    "uploadFotoProfil" : {
      "type" : "constant",
      "value" : [
        ""
      ],
      "exposed" : true
    },
    "uploadKTP" : {
      "type" : "constant",
      "value" : [
        ""
      ],
      "exposed" : true
    },
    "action" : {
      "type" : "constant",
      "value" : [
        ""
      ],
      "exposed" : true
    },
    "mode" : {
      "type" : "expression",
      "value" : [
        "var mode = \"view\";",
        "if($data.action==1 || $data.action==2){mode = \"edit\"}",
        "",
        "return mode;"
      ],
      "exposed" : false
    },
    "listJabatan" : {
      "type" : "url",
      "value" : [
        "../API/identity/group?p=0&c=100&f=parent_path=/entitas"
      ],
      "exposed" : false
    },
    "options" : {
      "type" : "json",
      "value" : [
        "{",
        "    \"jenisKelamin\":[\"Pria\",\"Wanita\"],",
        "    \"status\":[\"Belum Menikah\",\"Menikah\",\"Cerai\"]",
        "}"
      ],
      "exposed" : false
    }
  },
  "assets" : [ ],
  "inactiveAssets" : [ ],
  "webResources" : [ ],
  "hasValidationError" : false
}